README.md
setup.py
longformer/__init__.py
longformer/diagonaled_mm_tvm.py
longformer/longformer.py
longformer/sliding_chunks.py
longformer_chinese.egg-info/PKG-INFO
longformer_chinese.egg-info/SOURCES.txt
longformer_chinese.egg-info/dependency_links.txt
longformer_chinese.egg-info/requires.txt
longformer_chinese.egg-info/top_level.txt