Metadata-Version: 2.1
Name: longformer-chinese
Version: 0.0.0.1
Summary: Terry toolkit longformer chinese
Home-page: https://github.com/napoler/longformer-chinese
Author: Terry Chan
Author-email: napoler2008@gmail.com
License: UNKNOWN
Platform: UNKNOWN
